pyannote/audio/__init__.py
pyannote/audio/__main__.py
pyannote/audio/py.typed
pyannote/audio/augmentation/__init__.py
pyannote/audio/augmentation/mix.py
pyannote/audio/augmentation/registry.py
pyannote/audio/core/__init__.py
pyannote/audio/core/calibration.py
pyannote/audio/core/callback.py
pyannote/audio/core/inference.py
pyannote/audio/core/io.py
pyannote/audio/core/model.py
pyannote/audio/core/pipeline.py
pyannote/audio/core/plda.py
pyannote/audio/core/task.py
pyannote/audio/models/__init__.py
pyannote/audio/models/blocks/pooling.py
pyannote/audio/models/blocks/sincnet.py
pyannote/audio/models/embedding/__init__.py
pyannote/audio/models/embedding/debug.py
pyannote/audio/models/embedding/xvector.py
pyannote/audio/models/embedding/wespeaker/LICENSE.WeSpeaker
pyannote/audio/models/embedding/wespeaker/__init__.py
pyannote/audio/models/embedding/wespeaker/convert.py
pyannote/audio/models/embedding/wespeaker/resnet.py
pyannote/audio/models/segmentation/PyanNet.py
pyannote/audio/models/segmentation/SSeRiouSS.py
pyannote/audio/models/segmentation/__init__.py
pyannote/audio/models/segmentation/debug.py
pyannote/audio/models/separation/ToTaToNet.py
pyannote/audio/models/separation/__init__.py
pyannote/audio/pipelines/__init__.py
pyannote/audio/pipelines/clustering.py
pyannote/audio/pipelines/multilabel.py
pyannote/audio/pipelines/speaker_diarization.py
pyannote/audio/pipelines/speaker_verification.py
pyannote/audio/pipelines/speech_separation.py
pyannote/audio/pipelines/voice_activity_detection.py
pyannote/audio/pipelines/pyannoteai/__init__.py
pyannote/audio/pipelines/pyannoteai/local.py
pyannote/audio/pipelines/pyannoteai/sdk.py
pyannote/audio/pipelines/utils/__init__.py
pyannote/audio/pipelines/utils/diarization.py
pyannote/audio/pipelines/utils/getter.py
pyannote/audio/pipelines/utils/hook.py
pyannote/audio/pipelines/utils/oracle.py
pyannote/audio/sample/__init__.py
pyannote/audio/sample/sample.rttm
pyannote/audio/sample/sample.wav
pyannote/audio/tasks/__init__.py
pyannote_audio_notorchdeps-4.0.2.dist-info/METADATA
pyannote_audio_notorchdeps-4.0.2.dist-info/WHEEL
pyannote_audio_notorchdeps-4.0.2.dist-info/entry_points.txt
pyannote_audio_notorchdeps-4.0.2.dist-info/licenses/LICENSE
pyannote_audio_notorchdeps-4.0.2.dist-info/RECORD
